paniz/__init__.py
paniz/paniz.py
paniz-0.1.0.dist-info/LICENSE
paniz-0.1.0.dist-info/WHEEL
paniz-0.1.0.dist-info/METADATA
paniz-0.1.0.dist-info/RECORD
