Metadata-Version: 2.1
Name: paniz
Version: 0.1.0
Summary: Python package that eases the pain of concatenating Pandas categoricals!
Home-page: https://github.com/paradise1260/paniz
License: MIT
Author: Paniz Fazlali
Requires-Python: >=3.8,<4.0
Classifier: License :: OSI Approved :: MIT License
Classifier: Programming Language :: Python :: 3
Classifier: Programming Language :: Python :: 3.8
Classifier: Programming Language :: Python :: 3.9
Requires-Dist: pandas (>=1.2.4,<2.0.0)
Project-URL: Documentation, https://paniz.readthedocs.io/en/latest/
Project-URL: Repository, https://github.com/paradise1260/paniz
